sqlhere/__init__.py
sqlhere/sqlhere.py
sqlhere-0.1.4.dist-info/LICENSE.txt
sqlhere-0.1.4.dist-info/METADATA
sqlhere-0.1.4.dist-info/WHEEL
sqlhere-0.1.4.dist-info/top_level.txt
sqlhere-0.1.4.dist-info/RECORD
