Metadata-Version: 2.1
Name: sqlhere
Version: 0.1.4
Summary: sqlhere is made with an intention to help you create and use sql data locally. For Data Science Uses.
Author: Mayank Dwivedi (Data Scientist)
Author-email: mayankdwivediofficial@gmail.com
Classifier: Programming Language :: Python :: 3
Classifier: License :: OSI Approved :: MIT License
Classifier: Operating System :: OS Independent
License-File: LICENSE.txt
Requires-Dist: csv
Requires-Dist: json
Requires-Dist: sqlite3
Requires-Dist: datetime
Requires-Dist: time
